napari_mcp/__init__.py
napari_mcp/_version.py
napari_mcp/bridge_server.py
napari_mcp/napari.yaml
napari_mcp/py.typed
napari_mcp/server.py
napari_mcp/widget.py
napari_mcp/cli/__init__.py
napari_mcp/cli/main.py
napari_mcp/cli/install/__init__.py
napari_mcp/cli/install/base.py
napari_mcp/cli/install/claude_code.py
napari_mcp/cli/install/claude_desktop.py
napari_mcp/cli/install/cline_cursor.py
napari_mcp/cli/install/cline_vscode.py
napari_mcp/cli/install/codex_cli.py
napari_mcp/cli/install/cursor.py
napari_mcp/cli/install/gemini_cli.py
napari_mcp/cli/install/utils.py
napari_mcp-0.0.4.dist-info/licenses/LICENSE
napari_mcp-0.0.4.dist-info/METADATA
napari_mcp-0.0.4.dist-info/WHEEL
napari_mcp-0.0.4.dist-info/entry_points.txt
napari_mcp-0.0.4.dist-info/top_level.txt
napari_mcp-0.0.4.dist-info/RECORD
