Metadata-Version: 2.4
Name: napari-mcp
Version: 0.0.4
Summary: MCP server for remote control of napari viewers via Model Context Protocol
Author-email: Ilan Theodoro <ilan.silva@czbiohub.org>
Maintainer-email: Ilan Theodoro <ilan.silva@czbiohub.org>
License: MIT
Project-URL: Homepage, https://github.com/royerlab/napari-mcp
Project-URL: Repository, https://github.com/royerlab/napari-mcp
Project-URL: Documentation, https://github.com/royerlab/napari-mcp#readme
Project-URL: Bug Tracker, https://github.com/royerlab/napari-mcp/issues
Project-URL: Changelog, https://github.com/royerlab/napari-mcp/blob/main/CHANGELOG.md
Keywords: napari,mcp,microscopy,image-analysis,ai,claude
Classifier: Development Status :: 3 - Alpha
Classifier: Framework :: napari
Classifier: Intended Audience :: Science/Research
Classifier: Intended Audience :: Developers
Classifier: License :: OSI Approved :: MIT License
Classifier: Operating System :: OS Independent
Classifier: Programming Language :: Python :: 3
Classifier: Programming Language :: Python :: 3.10
Classifier: Programming Language :: Python :: 3.11
Classifier: Programming Language :: Python :: 3.12
Classifier: Programming Language :: Python :: 3.13
Classifier: Topic :: Scientific/Engineering :: Image Processing
Classifier: Topic :: Scientific/Engineering :: Visualization
Classifier: Topic :: Software Development :: Libraries :: Python Modules
Requires-Python: >=3.10
License-File: LICENSE
Requires-Dist: fastmcp>=2.10.3
Requires-Dist: napari>=0.5.5
Requires-Dist: pyqt6>=6.5.0
Requires-Dist: qtpy>=2.4.1
Requires-Dist: Pillow>=10.3.0
Requires-Dist: imageio>=2.34.0
Requires-Dist: numpy>=1.26.0
Requires-Dist: typer>=0.9.0
Requires-Dist: rich>=13.0.0
Requires-Dist: toml>=0.10.2
Provides-Extra: test
Requires-Dist: pytest>=8.4.0; extra == "test"
Requires-Dist: pytest-asyncio>=0.23.0; extra == "test"
Requires-Dist: pytest-cov>=4.0.0; extra == "test"
Requires-Dist: pytest-qt>=4.0.0; extra == "test"
Requires-Dist: pytest-xdist>=3.5.0; extra == "test"
Requires-Dist: pytest-timeout>=2.2.0; extra == "test"
Requires-Dist: pytest-benchmark>=4.0.0; extra == "test"
Requires-Dist: pytest-mock>=3.12.0; extra == "test"
Requires-Dist: pytest-random-order>=1.1.0; extra == "test"
Requires-Dist: pytest-forked>=1.6.0; extra == "test"
Requires-Dist: hypothesis>=6.100.0; extra == "test"
Requires-Dist: napari[pyqt6,testing]; extra == "test"
Requires-Dist: tox; extra == "test"
Provides-Extra: dev
Requires-Dist: ruff>=0.12.10; extra == "dev"
Requires-Dist: mypy>=1.17.0; extra == "dev"
Requires-Dist: types-toml>=0.10.8.20240310; extra == "dev"
Requires-Dist: types-Pillow>=10.0.0; extra == "dev"
Requires-Dist: pre-commit>=4.3.0; extra == "dev"
Requires-Dist: bandit>=1.8.6; extra == "dev"
Requires-Dist: black>=24.0.0; extra == "dev"
Provides-Extra: all
Requires-Dist: napari-mcp[dev,test]; extra == "all"
Dynamic: license-file
